coreg/__init__.py
coreg/_modidx.py
coreg/core.py
coreg-0.0.1.dist-info/LICENSE
coreg-0.0.1.dist-info/METADATA
coreg-0.0.1.dist-info/WHEEL
coreg-0.0.1.dist-info/entry_points.txt
coreg-0.0.1.dist-info/top_level.txt
coreg-0.0.1.dist-info/RECORD
