Metadata-Version: 2.1
Name: coreg
Version: 0.0.1
Summary: 'Notebook-based version of our coregistration tools'
Home-page: https://github.com/{user}/nbcoreg/
Author: michaelaye
Author-email: kmichael.aye@gmail.com
License: Apache Software License 2.0
Keywords: coregistration isis
Classifier: Development Status :: 3 - Alpha
Classifier: Intended Audience :: Developers
Classifier: Natural Language :: English
Classifier: Programming Language :: Python :: 3.10
Classifier: License :: OSI Approved :: Apache Software License
Requires-Python: >=3.10
License-File: LICENSE
Requires-Dist: pandas
Requires-Dist: kalasiris
Provides-Extra: dev
Requires-Dist: nbdev ; extra == 'dev'
